quart_uploads/__init__.py
quart_uploads/config.py
quart_uploads/exceptions.py
quart_uploads/file_ext.py
quart_uploads/py.typed
quart_uploads/route.py
quart_uploads/set.py
quart_uploads/utils.py
quart_uploads-0.0.4.dist-info/METADATA
quart_uploads-0.0.4.dist-info/WHEEL
quart_uploads-0.0.4.dist-info/RECORD
